CHANGELOG.rst
LICENSE
MANIFEST.in
README.rst
setup.cfg
setup.py
idoit/__about__.py
idoit/__init__.py
idoit/exception.py
idoit.egg-info/PKG-INFO
idoit.egg-info/SOURCES.txt
idoit.egg-info/dependency_links.txt
idoit.egg-info/not-zip-safe
idoit.egg-info/requires.txt
idoit.egg-info/top_level.txt
tests/__init__.py
tests/test01.py