Metadata-Version: 1.1
Name: idoit
Version: 0.1
Summary: Python Wrapper to access the i-doit JSON-RPC API
Home-page: https://github.com/DinoTools/python-idoit
Author: PhiBo (DinoTools)
Author-email: UNKNOWN
License: GPLv3
Keywords: i-doit
Platform: UNKNOWN
Classifier: Development Status :: 4 - Beta
Classifier: License :: OSI Approved :: GNU General Public License v3 or later (GPLv3+)
Classifier: Operating System :: OS Independent
Classifier: Programming Language :: Python
Classifier: Programming Language :: Python :: 2.7
Classifier: Programming Language :: Python :: 3
Classifier: Programming Language :: Python :: 3.2
Classifier: Programming Language :: Python :: 3.4
Classifier: Programming Language :: Python :: 3.5
Classifier: Programming Language :: Python :: 3.6
Classifier: Programming Language :: Python :: Implementation :: CPython
Classifier: Programming Language :: Python :: Implementation :: PyPy
